epb/__init__.py
epb/utils.py
epb-0.2.0.dist-info/LICENSE
epb-0.2.0.dist-info/WHEEL
epb-0.2.0.dist-info/METADATA
epb-0.2.0.dist-info/RECORD
