Metadata-Version: 2.1
Name: epb
Version: 0.2.0
Summary: Energy performance of buildings
Home-page: https://github.com/immoveable/epb-py
License: MIT
Author: Arthur White
Author-email: arthur@white.li
Requires-Python: >=3.7,<4.0
Classifier: License :: OSI Approved :: MIT License
Classifier: Programming Language :: Python :: 3
Classifier: Programming Language :: Python :: 3.7
Classifier: Programming Language :: Python :: 3.8
Classifier: Topic :: Utilities
Classifier: Typing :: Typed
Project-URL: Repository, https://github.com/immoveable/epb-py
